aiobrawlstats/__init__.py
aiobrawlstats/aiobrawlstats.py
aiobrawlstats/const/__init__.py
aiobrawlstats/const/const.py
aiobrawlstats/http/__init__.py
aiobrawlstats/http/http.py
aiobrawlstats/types/__init__.py
aiobrawlstats/types/brawlers/__init__.py
aiobrawlstats/types/brawlers/brawler.py
aiobrawlstats/types/players/__init__.py
aiobrawlstats/types/players/player.py
aiobrawlstats/types/players/player_battlelog.py
aiobrawlstats-1.0.1.dist-info/METADATA
aiobrawlstats-1.0.1.dist-info/WHEEL
aiobrawlstats-1.0.1.dist-info/top_level.txt
aiobrawlstats-1.0.1.dist-info/RECORD
