Metadata-Version: 2.1
Name: aiobrawlstats
Version: 1.0.1
Summary: Async BrawlStars API wrapper
Home-page: https://github.com/vladislavkovalskyi/aiobrawlstats
Author: vladislavkovalskyi
Author-email: v.darknesssb@gmail.com
License: MIT
Platform: UNKNOWN
Classifier: Operating System :: OS Independent
Requires-Dist: aiohttp
Requires-Dist: pydantic
